RecMath/__init__.py
RecMath/constant.py
RecMath/main.py
RecMath/matrix.py
RecMath/quaternion.py
RecMath/vector.py
recmath-1.0.dist-info/METADATA
recmath-1.0.dist-info/WHEEL
recmath-1.0.dist-info/top_level.txt
recmath-1.0.dist-info/RECORD
