Metadata-Version: 2.4
Name: RecMath
Version: 1.0
Summary: A strong, complete math library.
Author: 14Alfa
Dynamic: author
Dynamic: summary
